arc/__init__.py
arc/exceptions.py
arc/auth/__init__.py
arc/auth/jwt_validator.py
arc/auth/oauth2_client.py
arc/client/__init__.py
arc/client/arc_client.py
arc/client/stream_utils.py
arc/client/thread_manager.py
arc/core/__init__.py
arc/core/chat.py
arc/core/processing.py
arc/core/streaming.py
arc/core/validation.py
arc/core/webhooks.py
arc/crypto/__init__.py
arc/crypto/hybrid_tls.py
arc/crypto/oqs/lib/liboqs.0.15.0-rc1.dylib
arc/crypto/oqs/lib/liboqs.9.dylib
arc/crypto/oqs/lib/liboqs.dylib
arc/crypto/oqs/lib/ossl-modules/oqsprovider.dylib
arc/crypto/oqs/ssl/openssl.cnf
arc/fastapi/__init__.py
arc/fastapi/router.py
arc/models/__init__.py
arc/models/generated.py
arc/schemas/__init__.py
arc/schemas/agent-card.schema.json
arc/schemas/arc_schema.py
arc/schemas/arc_schema.yaml
arc/schemas/update_schema.py
arc/server/__init__.py
arc/server/arc_server.py
arc/server/decorators.py
arc/server/middleware.py
arc/server/sse.py
arc/server/storage/__init__.py
arc/server/storage/base.py
arc/server/storage/mongodb_storage.py
arc/server/storage/postgresql_storage.py
arc/server/storage/redis_storage.py
arc/starlette/__init__.py
arc/starlette/router.py
arc/utils/__init__.py
arc/utils/agent_card.py
arc/utils/config.py
arc/utils/logging.py
arc/utils/schema.py
arc/utils/testing.py
arc_sdk-1.3.1.dist-info/licenses/LICENSE
arc_sdk-1.3.1.dist-info/METADATA
arc_sdk-1.3.1.dist-info/WHEEL
arc_sdk-1.3.1.dist-info/entry_points.txt
arc_sdk-1.3.1.dist-info/top_level.txt
arc_sdk-1.3.1.dist-info/RECORD
